mongo_connector/__init__.py
mongo_connector/command_helper.py
mongo_connector/compat.py
mongo_connector/config.py
mongo_connector/connector.py
mongo_connector/constants.py
mongo_connector/errors.py
mongo_connector/get_last_oplog_timestamp.py
mongo_connector/gridfs_file.py
mongo_connector/locking_dict.py
mongo_connector/namespace_config.py
mongo_connector/oplog_manager.py
mongo_connector/test_utils.py
mongo_connector/util.py
mongo_connector/version.py
mongo_connector/doc_managers/__init__.py
mongo_connector/doc_managers/doc_manager_base.py
mongo_connector/doc_managers/doc_manager_simulator.py
mongo_connector/doc_managers/formatters.py
mongo_connector/doc_managers/mongo_doc_manager.py
mongo_connector-3.1.1.dist-info/LICENSE
mongo_connector-3.1.1.dist-info/METADATA
mongo_connector-3.1.1.dist-info/WHEEL
mongo_connector-3.1.1.dist-info/entry_points.txt
mongo_connector-3.1.1.dist-info/top_level.txt
mongo_connector-3.1.1.dist-info/RECORD
