Metadata-Version: 2.1
Name: mongo-connector
Version: 3.1.1
Summary: Mongo Connector
Home-page: https://github.com/yougov/mongo-connector
Author: MongoDB, Inc.
Author-email: mongodb-user@googlegroups.com
License: UNKNOWN
Keywords: mongo-connector,mongo,mongodb,solr,elasticsearch
Platform: any
Classifier: Development Status :: 4 - Beta
Classifier: Intended Audience :: Developers
Classifier: License :: OSI Approved :: Apache Software License
Classifier: Programming Language :: Python :: 3
Classifier: Topic :: Database
Classifier: Topic :: Software Development :: Libraries :: Python Modules
Classifier: Operating System :: Unix
Classifier: Operating System :: MacOS :: MacOS X
Classifier: Operating System :: Microsoft :: Windows
Classifier: Operating System :: POSIX
Requires-Python: >=3.4
Provides-Extra: elastic-aws
Provides-Extra: elastic2
Provides-Extra: solr
Provides-Extra: elastic
Provides-Extra: elastic2-aws
Provides-Extra: elastic5
